wazuh_sdk/__init__.py
wazuh_sdk/client.py
wazuh_sdk/constants.py
wazuh_sdk/enums.py
wazuh_sdk/exceptions.py
wazuh_sdk/interfaces.py
wazuh_sdk/query.py
wazuh_sdk/response.py
wazuh_sdk/utils.py
wazuh_sdk/endpoints/__init__.py
wazuh_sdk/endpoints/endpoints_v4.py
wazuh_sdk/managers/__init__.py
wazuh_sdk/managers/agents.py
wazuh_sdk/managers/groups.py
wazuh_sdk/managers/syscheck.py
wazuh_sdk/managers/wazuh.py
wazuh_sdk-0.1.0b0.dist-info/licenses/LICENSE
wazuh_sdk-0.1.0b0.dist-info/METADATA
wazuh_sdk-0.1.0b0.dist-info/WHEEL
wazuh_sdk-0.1.0b0.dist-info/top_level.txt
wazuh_sdk-0.1.0b0.dist-info/RECORD
